linkeds/__init__.py
linkeds/jsonifier.py
linkeds/list.py
linkeds/node.py
linkeds/queue.py
linkeds/stack.py
linkeds-1.0.0.dist-info/LICENSE
linkeds-1.0.0.dist-info/METADATA
linkeds-1.0.0.dist-info/WHEEL
linkeds-1.0.0.dist-info/top_level.txt
linkeds-1.0.0.dist-info/RECORD
