Metadata-Version: 2.1
Name: linkeds
Version: 1.0.0
Summary: LinkeDS is a versatile Python project with linked data structures — stack, queue, and list — offering adaptability in bounded and dynamic sizes.
Home-page: https://github.com/davidsantana06/linkeds
Author: David Santana
Author-email: davidsantana06@hotmail.com
License: UNKNOWN
Project-URL: Bug Tracker, https://github.com/davidsantana06/linkeds/issues
Platform: UNKNOWN
Classifier: Programming Language :: Python :: 3
Classifier: License :: OSI Approved :: MIT License
Classifier: Operating System :: OS Independent
Requires-Python: >=3.6
License-File: LICENSE
